help/__init__.py
rayvision_terragen/Analyze.exe
rayvision_terragen/__init__.py
rayvision_terragen/analyze_terragen.py
rayvision_terragen/constants.py
rayvision_terragen/tests/__init__.py
rayvision_terragen/tests/conftest.py
rayvision_terragen/tests/test_analyze_terragen.py
rayvision_terragen-1.0.1.dist-info/METADATA
rayvision_terragen-1.0.1.dist-info/WHEEL
rayvision_terragen-1.0.1.dist-info/top_level.txt
rayvision_terragen-1.0.1.dist-info/RECORD
